{
  "title":"The Matrix Exponential I",
  "description": "",
  "file": null,
  "learning_resource_types": ["Lecture Videos"],
  "resource_type": "Video",
  "file_type": "",
  "youtube_key":  "zreI4HllD80",
  "captions_file": "/courses/18-03sc-differential-equations-fall-2011/5289392d9fd454299742ba0adacac8f3_zreI4HllD80.vtt",
  "transcript_file": "/courses/18-03sc-differential-equations-fall-2011/5b399c61c5a9842a03bdb58e6150976b_zreI4HllD80.pdf",
  "thumbnail_file": "https://img.youtube.com/vi/zreI4HllD80/default.jpg",
  "archive_url": "http://www.archive.org/download/MIT18.03S06/mit-ocw-18.03-lec29-28apr2003-220k_512kb.mp4"}
